code/__init__.py
code/core.py
code/deliverable_util.py
code/finetuning.py
code/finetuning_core.py
code/train.py
sem_reject/__init__.py
sem_reject/core.py
sem_reject/deliverable_util.py
sem_reject/finetuning.py
sem_reject/finetuning_core.py
sem_reject/train.py
sem_reject-0.1.4.dist-info/METADATA
sem_reject-0.1.4.dist-info/WHEEL
sem_reject-0.1.4.dist-info/top_level.txt
sem_reject-0.1.4.dist-info/RECORD
